napari_tomoslice/__init__.py
napari_tomoslice/_constants.py
napari_tomoslice/cli.py
napari_tomoslice/console.py
napari_tomoslice/utils.py
napari_tomoslice/annotation/__init__.py
napari_tomoslice/annotation/cli.py
napari_tomoslice/annotation/tomoslice_app.py
napari_tomoslice/io/__init__.py
napari_tomoslice/io/dipoles.py
napari_tomoslice/io/paths.py
napari_tomoslice/io/points.py
napari_tomoslice/io/spheres.py
napari_tomoslice/io/volume.py
napari_tomoslice/pose_export/__init__.py
napari_tomoslice/pose_export/cli.py
napari_tomoslice/pose_export/dynamo.py
napari_tomoslice/pose_export/relion5.py
napari_tomoslice/pose_generation/__init__.py
napari_tomoslice/pose_generation/cli.py
napari_tomoslice/pose_generation/points.py
napari_tomoslice/pose_generation/spheres.py
napari_tomoslice/pose_generation/dipoles/__init__.py
napari_tomoslice/pose_generation/dipoles/cli.py
napari_tomoslice/pose_generation/dipoles/direct.py
napari_tomoslice/pose_generation/dipoles/disk.py
napari_tomoslice/pose_generation/paths/__init__.py
napari_tomoslice/pose_generation/paths/backbone.py
napari_tomoslice/pose_generation/paths/cli.py
napari_tomoslice/pose_generation/paths/helix.py
napari_tomoslice/pose_generation/paths/rings.py
napari_tomoslice/widgets/__init__.py
napari_tomoslice/widgets/tomoslice_widget.py
napari_tomoslice-0.2.1.dist-info/METADATA
napari_tomoslice-0.2.1.dist-info/WHEEL
napari_tomoslice-0.2.1.dist-info/entry_points.txt
napari_tomoslice-0.2.1.dist-info/licenses/LICENSE
napari_tomoslice-0.2.1.dist-info/RECORD
