Metadata-Version: 2.4
Name: napari-tomoslice
Version: 0.2.1
Summary: Tomogram visualisation and annotation in napari.
Project-URL: homepage, https://github.com/alisterburt/napari-tomoslice
Project-URL: repository, https://github.com/alisterburt/napari-tomoslice
Author-email: Alister Burt <alisterburt@gmail.com>
License: BSD 3-Clause License
License-File: LICENSE
Classifier: Development Status :: 3 - Alpha
Classifier: License :: OSI Approved :: BSD License
Classifier: Natural Language :: English
Classifier: Programming Language :: Python :: 3
Classifier: Programming Language :: Python :: 3.9
Classifier: Programming Language :: Python :: 3.10
Classifier: Programming Language :: Python :: 3.11
Classifier: Typing :: Typed
Requires-Python: >=3.8
Requires-Dist: dynamotable
Requires-Dist: morphosamplers
Requires-Dist: mrcfile
Requires-Dist: napari-threedee
Requires-Dist: napari[pyqt5]
Requires-Dist: starfile
Requires-Dist: typer
Provides-Extra: dev
Requires-Dist: black; extra == 'dev'
Requires-Dist: ipython; extra == 'dev'
Requires-Dist: mypy; extra == 'dev'
Requires-Dist: pdbpp; extra == 'dev'
Requires-Dist: pre-commit; extra == 'dev'
Requires-Dist: pytest; extra == 'dev'
Requires-Dist: pytest-cov; extra == 'dev'
Requires-Dist: rich; extra == 'dev'
Requires-Dist: ruff; extra == 'dev'
Provides-Extra: docs
Requires-Dist: mkdocs-material; extra == 'docs'
Provides-Extra: test
Requires-Dist: pytest-cov; extra == 'test'
Requires-Dist: pytest>=6.0; extra == 'test'
